{
  "id": 41990,
  "title": "Will the interest in \u201chospital\u201d change between 2026-02-03 and 2026-02-15 according to Google Trends?",
  "short_title": "Will Google Trend topic \"hospital\" rise?",
  "url_title": "Will Google Trend topic \"hospital\" rise?",
  "slug": "will-google-trend-topic-hospital-rise",
  "author_id": 276265,
  "author_username": "AutoQuestionsBot",
  "coauthors": [],
  "created_at": "2026-02-01T04:01:35.413558Z",
  "published_at": "2026-02-03T14:17:16Z",
  "edited_at": "2026-02-03T15:48:00.160193Z",
  "curation_status": "approved",
  "curation_status_updated_at": "2026-02-01T04:01:44.121189Z",
  "comment_count": 0,
  "status": "closed",
  "resolved": false,
  "actual_close_time": "2026-02-03T15:47:16Z",
  "scheduled_close_time": "2026-02-03T15:47:16Z",
  "scheduled_resolve_time": "2026-02-15T03:22:58Z",
  "actual_resolve_time": null,
  "open_time": "2026-02-03T14:17:16Z",
  "nr_forecasters": 95,
  "html_metadata_json": null,
  "projects": {
    "question_series": [
      {
        "id": 32933,
        "type": "question_series",
        "name": "MiniBench",
        "slug": "minibench",
        "header_image": null,
        "prize_pool": "1000.00",
        "start_date": "2026-02-02T05:00:00Z",
        "close_date": "2026-02-28T05:00:00Z",
        "forecasting_end_date": "2026-02-07T12:16:52Z",
        "html_metadata_json": null,
        "is_ongoing": true,
        "user_permission": null,
        "order": 0,
        "created_at": "2026-02-01T03:16:44.273506Z",
        "edited_at": "2026-02-03T23:20:41.199494Z",
        "score_type": "spot_peer_tournament",
        "default_permission": "forecaster",
        "visibility": "not_in_main_feed",
        "show_on_homepage": false,
        "is_current_content_translated": false,
        "bot_leaderboard_status": "include",
        "description_preview": "<p>Welcome to MiniBench! This is a bot-only competition where bot-makers attempt to push AI to its limits in predicting future events. MiniB"
      }
    ],
    "default_project": {
      "id": 32933,
      "type": "question_series",
      "name": "MiniBench",
      "slug": "minibench",
      "header_image": null,
      "prize_pool": "1000.00",
      "start_date": "2026-02-02T05:00:00Z",
      "close_date": "2026-02-28T05:00:00Z",
      "forecasting_end_date": "2026-02-07T12:16:52Z",
      "html_metadata_json": null,
      "is_ongoing": true,
      "user_permission": null,
      "order": 0,
      "created_at": "2026-02-01T03:16:44.273506Z",
      "edited_at": "2026-02-03T23:20:41.199494Z",
      "score_type": "spot_peer_tournament",
      "default_permission": "forecaster",
      "visibility": "not_in_main_feed",
      "show_on_homepage": false,
      "is_current_content_translated": false,
      "bot_leaderboard_status": "include",
      "description_preview": "<p>Welcome to MiniBench! This is a bot-only competition where bot-makers attempt to push AI to its limits in predicting future events. MiniB"
    }
  },
  "question": {
    "id": 41729,
    "title": "Will the interest in \u201chospital\u201d change between 2026-02-03 and 2026-02-15 according to Google Trends?",
    "created_at": "2026-02-01T04:01:35.414010Z",
    "open_time": "2026-02-03T14:17:16Z",
    "cp_reveal_time": "2026-02-03T15:47:16Z",
    "spot_scoring_time": "2026-02-03T15:47:16Z",
    "scheduled_resolve_time": "2026-02-15T03:22:58Z",
    "actual_resolve_time": null,
    "resolution_set_time": null,
    "scheduled_close_time": "2026-02-03T15:47:16Z",
    "actual_close_time": "2026-02-03T15:47:16Z",
    "type": "multiple_choice",
    "options": [
      "Increases",
      "Doesn't change",
      "Decreases"
    ],
    "all_options_ever": [
      "Increases",
      "Doesn't change",
      "Decreases"
    ],
    "options_history": [
      [
        "0001-01-01T00:00:00",
        [
          "Increases",
          "Doesn't change",
          "Decreases"
        ]
      ]
    ],
    "group_variable": "",
    "status": "closed",
    "possibilities": null,
    "resolution": null,
    "include_bots_in_aggregates": true,
    "question_weight": 1.0,
    "default_score_type": "spot_peer",
    "default_aggregation_method": "unweighted",
    "label": "",
    "unit": "",
    "open_upper_bound": false,
    "open_lower_bound": false,
    "inbound_outcome_count": null,
    "scaling": {
      "range_min": null,
      "range_max": null,
      "nominal_min": null,
      "nominal_max": null,
      "zero_point": null,
      "open_upper_bound": false,
      "open_lower_bound": false,
      "inbound_outcome_count": null,
      "continuous_range": null
    },
    "group_rank": null,
    "coherence_links": null,
    "coherence_link_aggregations": null,
    "description": "Google Trends is a free tool from Google that shows how often particular search terms are entered into Google relative to the total search volume across different regions and time periods. One of its main features is the \u201cinterest over time\u201d graph, which is scaled from 0 to 100. In this graph, 100 represents the peak popularity of the term during the selected time range and location, meaning the point in time when searches for that term were at their highest. A 0 does not mean no searches occurred, but rather that the search interest was too low to register compared to the peak values. Because the values are relative, the numbers for a given day can shift as new data is added or as the overall scale is recalibrated\u2014for example, a value of 40 on one day could later appear as 35 if the relative scaling changes. This effect can be reduced by specifying fixed start and end dates in the URL, which locks the scale for that chosen period and keeps the values consistent.\n\nThe current value of the topic \u201chospital\u201d at the time of writing this question (Feb 1, 2026) compared to the last 30 days is 53; seen at [this url](https://trends.google.com/trends/explore?geo=US&tz=0&q=hospital&date=2026-01-02%202026-02-01).\n\n`{\"format\":\"trends_interest_change_magnitude\",\"info\":{\"topic\":\"hospital\",\"trend_start\":\"2026-02-03\",\"trend_end\":\"2026-02-15\",\"verification_url\":\"https://trends.google.com/trends/explore?geo=US&tz=0&q=hospital&date=2026-01-16%202026-02-15\"}}`",
    "resolution_criteria": "This question resolves \u201cDoesn't change\u201d if the value on the timeline at [https://trends.google.com/trends/explore?geo=US&tz=0&q=hospital&date=2026-01-16%202026-02-15](https://trends.google.com/trends/explore?geo=US&tz=0&q=hospital&date=2026-01-16%202026-02-15) for 2026-02-15 is within 3 of the value at 2026-02-03. It resolves \u201cIncreases\u201d if the value is more than 3 greater, and resolves \u201cDecreases\u201d if the value is more than 3 lower.",
    "fine_print": "A script will be used to determine the resolution of this question. It will access the data on Google Trends using [SerpApi](https://serpapi.com/), and compare the height of the timeline for the two aforementioned dates. The specific python query will be structured as follows:\n```\nfrom serpapi import GoogleSearch\n\nsearch = GoogleSearch(params={\n  \"api_key\": API_KEY,\n  \"engine\": \"google_trends\",\n  \"data_type\": \"TIMESERIES\",\n  \"geo\": \"US\",\n  \"tz\": 0,\n  \"q\": \"hospital\",\n  \"date\": \"2026-01-16 2026-02-15\",\n})\nsearch.get_dict()\n```\nNote that there may be minor differences between the results returned by the API and the data appearing on the page. This seems to be due to the 'tz' parameter not having the intended effect in-browser. In this case, the API results will be considered authoritative.\nNote that the precision of the timeline will be 1 day, so this will compare the overall interest for the whole day as determined by Google Trends.\nDates are determined in UTC.\nIf the data is no longer available, or the script fails, this question will be annulled or manually resolved by a moderator.",
    "short_title": "Will Google Trend topic \"hospital\" rise?",
    "post_id": 41990,
    "aggregations": {
      "unweighted": {
        "history": [
          {
            "start_time": 1770128410.756225,
            "end_time": 1770128420.320945,
            "forecaster_count": 1,
            "interval_lower_bounds": [
              0.302,
              0.388,
              0.31
            ],
            "centers": [
              0.302,
              0.388,
              0.31
            ],
            "interval_upper_bounds": [
              0.302,
              0.388,
              0.31
            ]
          },
          {
            "start_time": 1770128420.320945,
            "end_time": 1770128439.923355,
            "forecaster_count": 2,
            "interval_lower_bounds": [
              0.22,
              0.388,
              0.31
            ],
            "centers": [
              0.261,
              0.40900000000000003,
              0.32999999999999996
            ],
            "interval_upper_bounds": [
              0.302,
              0.42999999999999994,
              0.35
            ]
          },
          {
            "start_time": 1770128439.923355,
            "end_time": 1770128473.142355,
            "forecaster_count": 3,
            "interval_lower_bounds": [
              0.10416072955257906,
              0.4041796311146752,
              0.2604156133077156
            ],
            "centers": [
              0.22915360501567394,
              0.44793103448275856,
              0.3229153605015674
            ],
            "interval_upper_bounds": [
              0.3145654032487888,
              0.6771050521251002,
              0.3645818586308019
            ]
          },
          {
            "start_time": 1770128473.142355,
            "end_time": 1770128507.374125,
            "forecaster_count": 4,
            "interval_lower_bounds": [
              0.15920466758790114,
              0.4069634709076471,
              0.22388125534645
            ],
            "centers": [
              0.25870758483033934,
              0.4626846307385229,
              0.27860778443113776
            ],
            "interval_upper_bounds": [
              0.299503780899739,
              0.5721369089777433,
              0.3283591745081266
            ]
          },
          {
            "start_time": 1770128507.374125,
            "end_time": 1770128667.291031,
            "forecaster_count": 5,
            "interval_lower_bounds": [
              0.22,
              0.43,
              0.25
            ],
            "centers": [
              0.27999999999999997,
              0.45999999999999996,
              0.26
            ],
            "interval_upper_bounds": [
              0.3,
              0.5,
              0.31
            ]
          },
          {
            "start_time": 1770128667.291031,
            "end_time": 1770128717.131439,
            "forecaster_count": 6,
            "interval_lower_bounds": [
              0.12356424521613488,
              0.3959248329557348,
              0.2550997503995403
            ],
            "centers": [
              0.25509723643807575,
              0.4540890481064483,
              0.29081371545547596
            ],
            "interval_upper_bounds": [
              0.3061166837256909,
              0.5102124136027509,
              0.35713965055935637
            ]
          },
          {
            "start_time": 1770128717.131439,
            "end_time": 1770128733.359157,
            "forecaster_count": 7,
            "interval_lower_bounds": [
              0.11872232532497817,
              0.3267933502549678,
              0.24509943857645827
            ],
            "centers": [
              0.27451327433628314,
              0.42156342182890855,
              0.30392330383480826
            ],
            "interval_upper_bounds": [
              0.2960821744627054,
              0.4901900253824518,
              0.34313921400704156
            ]
          },
          {
            "start_time": 1770128733.359157,
            "end_time": 1770128736.942771,
            "forecaster_count": 8,
            "interval_lower_bounds": [
              0.16969967910533446,
              0.3588709771468299,
              0.2238811849984242
            ],
            "centers": [
              0.2736327345309381,
              0.4427844311377245,
              0.28358283433133735
            ],
            "interval_upper_bounds": [
              0.2995034657956813,
              0.5273612325909978,
              0.3399677253679775
            ]
          },
          {
            "start_time": 1770128736.942771,
            "end_time": 1770128739.656791,
            "forecaster_count": 9,
            "interval_lower_bounds": [
              0.2020188374798304,
              0.39192255847760016,
              0.20201854882705944
            ],
            "centers": [
              0.27272543059777105,
              0.4646504559270517,
              0.2626241134751773
            ],
            "interval_upper_bounds": [
              0.3030282562197456,
              0.5656614246068457,
              0.33669758137843236
            ]
          },
          {
            "start_time": 1770128739.656791,
            "end_time": 1770128746.010181,
            "forecaster_count": 10,
            "interval_lower_bounds": [
              0.20407745493284318,
              0.39592613442511093,
              0.20407811026150482
            ],
            "centers": [
              0.24999488229273287,
              0.4898055271238485,
              0.2601995905834186
            ],
            "interval_upper_bounds": [
              0.30611618239926475,
              0.6122569089048107,
              0.34013018376917464
            ]
          },
          {
            "start_time": 1770128746.010181,
            "end_time": 1770128746.218177,
            "forecaster_count": 11,
            "interval_lower_bounds": [
              0.18555889818557866,
              0.40001315408479843,
              0.2061799379524302
            ],
            "centers": [
              0.226794208893485,
              0.5154808686659773,
              0.25772492244053774
            ],
            "interval_upper_bounds": [
              0.3092648303092977,
              0.6185770423991728,
              0.343633229920717
            ]
          },
          {
            "start_time": 1770128746.218177,
            "end_time": 1770128748.625452,
            "forecaster_count": 12,
            "interval_lower_bounds": [
              0.1968797643797644,
              0.42385238104577727,
              0.20724416724416728
            ],
            "centers": [
              0.21760395010395014,
              0.5492463617463618,
              0.23314968814968817
            ],
            "interval_upper_bounds": [
              0.30050069300069304,
              0.621788334052485,
              0.33331770231770236
            ]
          },
          {
            "start_time": 1770128748.625452,
            "end_time": 1770128750.781166,
            "forecaster_count": 13,
            "interval_lower_bounds": [
              0.1874858934169279,
              0.4479407374234961,
              0.20831765935214214
            ],
            "centers": [
              0.2083176593521421,
              0.5833646812957158,
              0.2083176593521421
            ],
            "interval_upper_bounds": [
              0.2916447230929989,
              0.6250335871025525,
              0.32289237199582027
            ]
          },
          {
            "start_time": 1770128750.781166,
            "end_time": 1770128751.396614,
            "forecaster_count": 14,
            "interval_lower_bounds": [
              0.183667202807428,
              0.43878687693046253,
              0.20407419427316073
            ],
            "centers": [
              0.21427840327533262,
              0.5765455475946776,
              0.20917604912998977
            ],
            "interval_upper_bounds": [
              0.2857045377004435,
              0.6122607585076221,
              0.3163150011233991
            ]
          },
          {
            "start_time": 1770128751.396614,
            "end_time": 1770128752.623169,
            "forecaster_count": 15,
            "interval_lower_bounds": [
              0.18555635987590488,
              0.4433168235998476,
              0.18555635987590485
            ],
            "centers": [
              0.20617373319544985,
              0.5876525336091003,
              0.20617373319544985
            ],
            "interval_upper_bounds": [
              0.2886432264736298,
              0.6598203886137266,
              0.3195692864529472
            ]
          },
          {
            "start_time": 1770128752.623169,
            "end_time": 1770128755.120599,
            "forecaster_count": 16,
            "interval_lower_bounds": [
              0.18484505893691155,
              0.4495009049264368,
              0.1767641843971631
            ],
            "centers": [
              0.20706686930091187,
              0.590916919959473,
              0.20201621073961498
            ],
            "interval_upper_bounds": [
              0.2777726295500037,
              0.6414226396141289,
              0.28787310030395136
            ]
          },
          {
            "start_time": 1770128755.120599,
            "end_time": 1770128755.414066,
            "forecaster_count": 17,
            "interval_lower_bounds": [
              0.1897894429010089,
              0.46940006105334986,
              0.18366632548618217
            ],
            "centers": [
              0.21427840327533265,
              0.5816479017400206,
              0.20407369498464686
            ],
            "interval_upper_bounds": [
              0.275500804211142,
              0.6428739966600228,
              0.26529580348004095
            ]
          },
          {
            "start_time": 1770128755.414066,
            "end_time": 1770128756.359738,
            "forecaster_count": 18,
            "interval_lower_bounds": [
              0.18181481206909336,
              0.4646526208228335,
              0.17171377912867272
            ],
            "centers": [
              0.20706686930091187,
              0.590916919959473,
              0.20201621073961498
            ],
            "interval_upper_bounds": [
              0.27272221810364,
              0.6464732115795945,
              0.2626210739614995
            ]
          },
          {
            "start_time": 1770128756.359738,
            "end_time": 1770128758.295867,
            "forecaster_count": 19,
            "interval_lower_bounds": [
              0.17999999999999997,
              0.45999999999999985,
              0.16999999999999996
            ],
            "centers": [
              0.19999999999999998,
              0.5999999999999999,
              0.19999999999999998
            ],
            "interval_upper_bounds": [
              0.26999999999999996,
              0.6439999999999999,
              0.25999999999999995
            ]
          },
          {
            "start_time": 1770128758.295867,
            "end_time": 1770128758.650821,
            "forecaster_count": 20,
            "interval_lower_bounds": [
              0.16799999999999995,
              0.47999999999999987,
              0.16499999999999995
            ],
            "centers": [
              0.19999999999999998,
              0.5999999999999999,
              0.19999999999999998
            ],
            "interval_upper_bounds": [
              0.26699999999999996,
              0.6469999999999999,
              0.25499999999999995
            ]
          },
          {
            "start_time": 1770128758.650821,
            "end_time": 1770128758.935079,
            "forecaster_count": 21,
            "interval_lower_bounds": [
              0.17999999999999997,
              0.4999999999999999,
              0.16999999999999996
            ],
            "centers": [
              0.19999999999999998,
              0.5999999999999999,
              0.19999999999999998
            ],
            "interval_upper_bounds": [
              0.26399999999999996,
              0.6439999999999999,
              0.24999999999999997
            ]
          },
          {
            "start_time": 1770128758.935079,
            "end_time": 1770128761.737043,
            "forecaster_count": 22,
            "interval_lower_bounds": [
              0.15599999999999997,
              0.4999999999999999,
              0.16
            ],
            "centers": [
              0.19999999999999998,
              0.5999999999999999,
              0.19999999999999998
            ],
            "interval_upper_bounds": [
              0.26399999999999996,
              0.6499999999999999,
              0.24999999999999997
            ]
          },
          {
            "start_time": 1770128761.737043,
            "end_time": 1770128761.779934,
            "forecaster_count": 23,
            "interval_lower_bounds": [
              0.15599999999999997,
              0.4999999999999999,
              0.16
            ],
            "centers": [
              0.19999999999999998,
              0.5999999999999999,
              0.19999999999999998
            ],
            "interval_upper_bounds": [
              0.26999999999999996,
              0.6499999999999999,
              0.24999999999999997
            ]
          },
          {
            "start_time": 1770128761.779934,
            "end_time": 1770128761.851028,
            "forecaster_count": 24,
            "interval_lower_bounds": [
              0.148,
              0.4999999999999999,
              0.155
            ],
            "centers": [
              0.19999999999999998,
              0.5999999999999999,
              0.19999999999999998
            ],
            "interval_upper_bounds": [
              0.26699999999999996,
              0.6599999999999999,
              0.24299999999999997
            ]
          },
          {
            "start_time": 1770128761.851028,
            "end_time": 1770128764.725524,
            "forecaster_count": 25,
            "interval_lower_bounds": [
              0.15599999999999997,
              0.4999999999999999,
              0.16
            ],
            "centers": [
              0.19999999999999998,
              0.5999999999999999,
              0.19999999999999998
            ],
            "interval_upper_bounds": [
              0.26399999999999996,
              0.6499999999999999,
              0.23599999999999996
            ]
          },
          {
            "start_time": 1770128764.725524,
            "end_time": 1770128764.967404,
            "forecaster_count": 26,
            "interval_lower_bounds": [
              0.15522535416970937,
              0.4975091483699269,
              0.1492552395209581
            ],
            "centers": [
              0.20398203592814373,
              0.5970109780439122,
              0.19900698602794412
            ],
            "interval_upper_bounds": [
              0.2626890609025851,
              0.6666622588157021,
              0.23482824351297402
            ]
          },
          {
            "start_time": 1770128764.967404,
            "end_time": 1770128765.450878,
            "forecaster_count": 27,
            "interval_lower_bounds": [
              0.15599999999999997,
              0.4999999999999999,
              0.15
            ],
            "centers": [
              0.19999999999999998,
              0.5999999999999999,
              0.19999999999999998
            ],
            "interval_upper_bounds": [
              0.26399999999999996,
              0.6699999999999999,
              0.23599999999999996
            ]
          },
          {
            "start_time": 1770128765.450878,
            "end_time": 1770128765.462427,
            "forecaster_count": 28,
            "interval_lower_bounds": [
              0.16799999999999998,
              0.51,
              0.14400000000000002
            ],
            "centers": [
              0.2,
              0.6,
              0.19999999999999998
            ],
            "interval_upper_bounds": [
              0.257,
              0.67,
              0.22799999999999998
            ]
          },
          {
            "start_time": 1770128765.462427,
            "end_time": 1770128766.081928,
            "forecaster_count": 29,
            "interval_lower_bounds": [
              0.17999999999999994,
              0.4999999999999999,
              0.15
            ],
            "centers": [
              0.2,
              0.5999999999999999,
              0.19999999999999998
            ],
            "interval_upper_bounds": [
              0.24999999999999997,
              0.6699999999999999,
              0.23599999999999996
            ]
          },
          {
            "start_time": 1770128766.081928,
            "end_time": 1770128767.692487,
            "forecaster_count": 30,
            "interval_lower_bounds": [
              0.17999999999999997,
              0.4999999999999999,
              0.15
            ],
            "centers": [
              0.19999999999999998,
              0.5999999999999999,
              0.19999999999999998
            ],
            "interval_upper_bounds": [
              0.24999999999999997,
              0.6699999999999999,
              0.23599999999999996
            ]
          },
          {
            "start_time": 1770128767.692487,
            "end_time": 1770128769.760048,
            "forecaster_count": 31,
            "interval_lower_bounds": [
              0.17999999999999994,
              0.4999999999999999,
              0.15
            ],
            "centers": [
              0.2,
              0.5999999999999999,
              0.19999999999999998
            ],
            "interval_upper_bounds": [
              0.26399999999999996,
              0.6699999999999999,
              0.23599999999999996
            ]
          },
          {
            "start_time": 1770128769.760048,
            "end_time": 1770128769.857437,
            "forecaster_count": 32,
            "interval_lower_bounds": [
              0.16799999999999995,
              0.4999999999999999,
              0.155
            ],
            "centers": [
              0.19999999999999998,
              0.5999999999999999,
              0.19999999999999998
            ],
            "interval_upper_bounds": [
              0.25699999999999995,
              0.6599999999999999,
              0.24299999999999997
            ]
          },
          {
            "start_time": 1770128769.857437,
            "end_time": 1770128771.973131,
            "forecaster_count": 33,
            "interval_lower_bounds": [
              0.17999999999999994,
              0.4999999999999999,
              0.15
            ],
            "centers": [
              0.2,
              0.5999999999999999,
              0.19999999999999998
            ],
            "interval_upper_bounds": [
              0.24999999999999997,
              0.6499999999999999,
              0.23599999999999996
            ]
          },
          {
            "start_time": 1770128771.973131,
            "end_time": 1770128772.246215,
            "forecaster_count": 34,
            "interval_lower_bounds": [
              0.1791061778881262,
              0.4975091483699269,
              0.13731482035928144
            ],
            "centers": [
              0.20398203592814373,
              0.5970109780439122,
              0.1990069860279441
            ],
            "interval_upper_bounds": [
              0.24875858040017526,
              0.6666622588157021,
              0.23482824351297402
            ]
          },
          {
            "start_time": 1770128772.246215,
            "end_time": 1770128774.884384,
            "forecaster_count": 35,
            "interval_lower_bounds": [
              0.17999999999999994,
              0.4999999999999999,
              0.13799999999999998
            ],
            "centers": [
              0.2,
              0.5999999999999999,
              0.19999999999999998
            ],
            "interval_upper_bounds": [
              0.24999999999999997,
              0.6699999999999999,
              0.23599999999999996
            ]
          },
          {
            "start_time": 1770128774.884384,
            "end_time": 1770128776.163363,
            "forecaster_count": 36,
            "interval_lower_bounds": [
              0.1791061778881262,
              0.5074593313373253,
              0.14328502994011977
            ],
            "centers": [
              0.20398203592814373,
              0.5970109780439122,
              0.1990069860279441
            ],
            "interval_upper_bounds": [
              0.24875858040017526,
              0.6567120758483035,
              0.22686796407185625
            ]
          },
          {
            "start_time": 1770128776.163363,
            "end_time": 1770128779.367777,
            "forecaster_count": 37,
            "interval_lower_bounds": [
              0.1782210242587601,
              0.49504303210857326,
              0.14851787487586893
            ],
            "centers": [
              0.20792452830188676,
              0.5940516385302879,
              0.1980238331678252
            ],
            "interval_upper_bounds": [
              0.24752920035938897,
              0.6435559417411452,
              0.23366812313803373
            ]
          },
          {
            "start_time": 1770128779.367777,
            "end_time": 1770128786.279482,
            "forecaster_count": 38,
            "interval_lower_bounds": [
              0.1782210242587601,
              0.49504303210857326,
              0.1366364448857994
            ],
            "centers": [
              0.20792452830188676,
              0.5940516385302879,
              0.19802383316782518
            ],
            "interval_upper_bounds": [
              0.24752920035938897,
              0.6633576630254883,
              0.2336681231380337
            ]
          },
          {
            "start_time": 1770128786.279482,
            "end_time": 1770128788.506848,
            "forecaster_count": 39,
            "interval_lower_bounds": [
              0.17822102425876007,
              0.49504303210857326,
              0.1366364448857994
            ],
            "centers": [
              0.2079245283018868,
              0.5940516385302879,
              0.1980238331678252
            ],
            "interval_upper_bounds": [
              0.24752920035938897,
              0.6633576630254883,
              0.2475297914597815
            ]
          },
          {
            "start_time": 1770128788.506848,
            "end_time": 1770128788.556616,
            "forecaster_count": 40,
            "interval_lower_bounds": [
              0.17822102425876007,
              0.49504303210857326,
              0.14257715988083416
            ],
            "centers": [
              0.20792452830188676,
              0.5940516385302879,
              0.1980238331678252
            ],
            "interval_upper_bounds": [
              0.24752920035938897,
              0.6534568023833167,
              0.251490268123138
            ]
          },
          {
            "start_time": 1770128788.556616,
            "end_time": 1770128791.232524,
            "forecaster_count": 41,
            "interval_lower_bounds": [
              0.17822102425876007,
              0.49504303210857326,
              0.14851787487586893
            ],
            "centers": [
              0.2079245283018868,
              0.5940516385302879,
              0.1980238331678252
            ],
            "interval_upper_bounds": [
              0.24752920035938897,
              0.6435559417411452,
              0.2475297914597815
            ]
          },
          {
            "start_time": 1770128791.232524,
            "end_time": 1770128792.938052,
            "forecaster_count": 42,
            "interval_lower_bounds": [
              0.1782210242587601,
              0.49504303210857326,
              0.14851787487586893
            ],
            "centers": [
              0.20792452830188676,
              0.5940516385302879,
              0.19802383316782518
            ],
            "interval_upper_bounds": [
              0.24752920035938897,
              0.6435559417411452,
              0.2475297914597815
            ]
          },
          {
            "start_time": 1770128792.938052,
            "end_time": 1770128793.706262,
            "forecaster_count": 43,
            "interval_lower_bounds": [
              0.17822102425876007,
              0.49504303210857326,
              0.14851787487586893
            ],
            "centers": [
              0.20792452830188676,
              0.5940516385302879,
              0.1980238331678252
            ],
            "interval_upper_bounds": [
              0.24752920035938897,
              0.6435559417411452,
              0.2554507447864945
            ]
          },
          {
            "start_time": 1770128793.706262,
            "end_time": 1770128794.969956,
            "forecaster_count": 44,
            "interval_lower_bounds": [
              0.17822102425876007,
              0.49504303210857326,
              0.14257715988083416
            ],
            "centers": [
              0.20792452830188676,
              0.5940516385302879,
              0.19802383316782518
            ],
            "interval_upper_bounds": [
              0.24752920035938897,
              0.6497439796425024,
              0.251490268123138
            ]
          },
          {
            "start_time": 1770128794.969956,
            "end_time": 1770128795.255064,
            "forecaster_count": 45,
            "interval_lower_bounds": [
              0.17822102425876007,
              0.49504303210857326,
              0.1366364448857994
            ],
            "centers": [
              0.2079245283018868,
              0.5940516385302879,
              0.19802383316782515
            ],
            "interval_upper_bounds": [
              0.24752920035938897,
              0.6435559417411452,
              0.2475297914597815
            ]
          },
          {
            "start_time": 1770128795.255064,
            "end_time": 1770128797.689108,
            "forecaster_count": 46,
            "interval_lower_bounds": [
              0.17839718697162818,
              0.49553429423459244,
              0.13677173879798135
            ],
            "centers": [
              0.2120944333996024,
              0.5946411530815109,
              0.19326441351888668
            ],
            "interval_upper_bounds": [
              0.247773870793928,
              0.6441945825049702,
              0.24777488912677778
            ]
          },
          {
            "start_time": 1770128797.689108,
            "end_time": 1770128798.577732,
            "forecaster_count": 47,
            "interval_lower_bounds": [
              0.17857373682048477,
              0.49602653399668334,
              0.12897062058130404
            ],
            "centers": [
              0.2162726368159204,
              0.59523184079602,
              0.18849552238805975
            ],
            "interval_upper_bounds": [
              0.24801907891733996,
              0.6572351575456055,
              0.24802042419481543
            ]
          },
          {
            "start_time": 1770128798.577732,
            "end_time": 1770128799.128568,
            "forecaster_count": 48,
            "interval_lower_bounds": [
              0.18137029875541272,
              0.5054449801192843,
              0.1328075023542953
            ],
            "centers": [
              0.2170497017892644,
              0.5946411530815109,
              0.18830914512922467
            ],
            "interval_upper_bounds": [
              0.24777363217952558,
              0.6503887611829026,
              0.24083748561263996
            ]
          },
          {
            "start_time": 1770128799.128568,
            "end_time": 1770128800.15741,
            "forecaster_count": 49,
            "interval_lower_bounds": [
              0.1841613252685745,
              0.504943892750745,
              0.12871583128625938
            ],
            "centers": [
              0.21782522343594835,
              0.594051638530288,
              0.18812313803376368
            ],
            "interval_upper_bounds": [
              0.2475286629953959,
              0.6435559417411454,
              0.23366873987351697
            ]
          },
          {
            "start_time": 1770128800.15741,
            "end_time": 1770128805.966155,
            "forecaster_count": 50,
            "interval_lower_bounds": [
              0.18470908185440058,
              0.5064501494023907,
              0.12909847242047853
            ],
            "centers": [
              0.21847310756972108,
              0.5958237051792828,
              0.18570318725099602
            ],
            "interval_upper_bounds": [
              0.24826489496559215,
              0.6454756806108898,
              0.23436338070179175
            ]
          },
          {
            "start_time": 1770128805.966155,
            "end_time": 1770128820.588241,
            "forecaster_count": 51,
            "interval_lower_bounds": [
              0.1841613252685745,
              0.504943892750745,
              0.12871583128625938
            ],
            "centers": [
              0.21782522343594835,
              0.594051638530288,
              0.18812313803376368
            ],
            "interval_upper_bounds": [
              0.2475286629953959,
              0.6435559417411454,
              0.23366873987351697
            ]
          },
          {
            "start_time": 1770128820.588241,
            "end_time": 1770128827.305303,
            "forecaster_count": 52,
            "interval_lower_bounds": [
              0.1841613252685745,
              0.4999934624296592,
              0.13267631840275965
            ],
            "centers": [
              0.21782522343594835,
              0.594051638530288,
              0.18812313803376368
            ],
            "interval_upper_bounds": [
              0.2475286629953959,
              0.640585683548494,
              0.24059959232739248
            ]
          },
          {
            "start_time": 1770128827.305303,
            "end_time": 1770128850.019052,
            "forecaster_count": 53,
            "interval_lower_bounds": [
              0.1841613252685745,
              0.4950430321085733,
              0.13663680551925994
            ],
            "centers": [
              0.21782522343594835,
              0.594051638530288,
              0.1881231380337637
            ],
            "interval_upper_bounds": [
              0.2475286629953959,
              0.6376154253558425,
              0.247530444781268
            ]
          },
          {
            "start_time": 1770128850.019052,
            "end_time": 1770128855.178531,
            "forecaster_count": 54,
            "interval_lower_bounds": [
              0.17822063735668506,
              0.49504310164979604,
              0.1366366205790238
            ],
            "centers": [
              0.21782522343594835,
              0.5891012909632573,
              0.19307348560079446
            ],
            "interval_upper_bounds": [
              0.2475286629953959,
              0.6376155149249373,
              0.25545107325643573
            ]
          },
          {
            "start_time": 1770128855.178531,
            "end_time": 1770128861.011867,
            "forecaster_count": 55,
            "interval_lower_bounds": [
              0.178220637356685,
              0.4950431723696833,
              0.1366364448857994
            ],
            "centers": [
              0.21782522343594832,
              0.5841509433962264,
              0.19802383316782515
            ],
            "interval_upper_bounds": [
              0.24752866299539583,
              0.6376156060121522,
              0.2574309831181728
            ]
          },
          {
            "start_time": 1770128861.011867,
            "end_time": 1770128861.182668,
            "forecaster_count": 56,
            "interval_lower_bounds": [
              0.17910587915078932,
              0.49750925499428494,
              0.14328502994011974
            ],
            "centers": [
              0.21890718562874248,
              0.5820858283433135,
              0.1990069860279441
            ],
            "interval_upper_bounds": [
              0.2487581654872074,
              0.6388018834126619,
              0.2606991516966068
            ]
          },
          {
            "start_time": 1770128861.182668,
            "end_time": 1770128864.47895,
            "forecaster_count": 57,
            "interval_lower_bounds": [
              0.18,
              0.5,
              0.14999999999999994
            ],
            "centers": [
              0.21999999999999997,
              0.5800000000000001,
              0.19999999999999998
            ],
            "interval_upper_bounds": [
              0.25,
              0.64,
              0.26399999999999996
            ]
          },
          {
            "start_time": 1770128864.47895,
            "end_time": 1770128867.939561,
            "forecaster_count": 58,
            "interval_lower_bounds": [
              0.17928400366756528,
              0.49800541339002874,
              0.1374513086913087
            ],
            "centers": [
              0.21812887112887108,
              0.5826663336663337,
              0.19920479520479517
            ],
            "interval_upper_bounds": [
              0.24900556064939625,
              0.6414309724463569,
              0.26295032967032966
            ]
          },
          {
            "start_time": 1770128867.939561,
            "end_time": 1770128869.102244,
            "forecaster_count": 59,
            "interval_lower_bounds": [
              0.18,
              0.47400000000000003,
              0.13799999999999998
            ],
            "centers": [
              0.21999999999999997,
              0.5800000000000001,
              0.19999999999999998
            ],
            "interval_upper_bounds": [
              0.25,
              0.644,
              0.26999999999999996
            ]
          },
          {
            "start_time": 1770128869.102244,
            "end_time": 1770128879.22127,
            "forecaster_count": 60,
            "interval_lower_bounds": [
              0.17928400366756528,
              0.48505727264188797,
              0.14342745254745254
            ],
            "centers": [
              0.21812887112887108,
              0.5826663336663337,
              0.19920479520479517
            ],
            "interval_upper_bounds": [
              0.24900556064939625,
              0.6394389507927969,
              0.2659384015984016
            ]
          },
          {
            "start_time": 1770128879.22127,
            "end_time": 1770128896.136506,
            "forecaster_count": 61,
            "interval_lower_bounds": [
              0.18000000000000005,
              0.47400000000000003,
              0.14999999999999994
            ],
            "centers": [
              0.21999999999999997,
              0.5800000000000001,
              0.19999999999999998
            ],
            "interval_upper_bounds": [
              0.25,
              0.64,
              0.26999999999999996
            ]
          },
          {
            "start_time": 1770128896.136506,
            "end_time": 1770128899.750946,
            "forecaster_count": 62,
            "interval_lower_bounds": [
              0.1801798976728833,
              0.4744750830909848,
              0.15014984939759032
            ],
            "centers": [
              0.219218875502008,
              0.580581325301205,
              0.20019979919678715
            ],
            "interval_upper_bounds": [
              0.2502498578790046,
              0.6406414624013296,
              0.2902897088353413
            ]
          },
          {
            "start_time": 1770128899.750946,
            "end_time": 1770128923.569016,
            "forecaster_count": 63,
            "interval_lower_bounds": [
              0.1803601493707067,
              0.47495112112285565,
              0.138276
            ],
            "centers": [
              0.21843618090452255,
              0.5811638190954774,
              0.2004
            ],
            "interval_upper_bounds": [
              0.2505002074593149,
              0.6452922405129095,
              0.2905799999999999
            ]
          },
          {
            "start_time": 1770128923.569016,
            "end_time": 1770128932.033373,
            "forecaster_count": 64,
            "interval_lower_bounds": [
              0.17958165361774925,
              0.48087650684501915,
              0.1336886891260841
            ],
            "centers": [
              0.2168282188125417,
              0.5836364242828553,
              0.19953535690460306
            ],
            "interval_upper_bounds": [
              0.24941896335798508,
              0.6454919085658245,
              0.2793494996664443
            ]
          },
          {
            "start_time": 1770128932.033373,
            "end_time": 1770128933.408254,
            "forecaster_count": 65,
            "interval_lower_bounds": [
              0.17880990215364176,
              0.4867507838490507,
              0.1370879442045832
            ],
            "centers": [
              0.21523414148123546,
              0.5860876785121223,
              0.1986781800066423
            ],
            "interval_upper_bounds": [
              0.24834708632450248,
              0.6397296016301809,
              0.2682155430089671
            ]
          },
          {
            "start_time": 1770128933.408254,
            "end_time": 1770128941.229964,
            "forecaster_count": 66,
            "interval_lower_bounds": [
              0.17037007853636696,
              0.4853427192550999,
              0.13669271876810996
            ],
            "centers": [
              0.21254987995695007,
              0.5893447305240499,
              0.19810538951899992
            ],
            "interval_upper_bounds": [
              0.24763092810518453,
              0.63787900244956,
              0.2674422758506499
            ]
          },
          {
            "start_time": 1770128941.229964,
            "end_time": 1770128954.25104,
            "forecaster_count": 67,
            "interval_lower_bounds": [
              0.15561164111467496,
              0.4728164166829177,
              0.1376565532766383
            ],
            "centers": [
              0.21197098549274637,
              0.5885267633816909,
              0.19950225112556277
            ],
            "interval_upper_bounds": [
              0.2493776299914663,
              0.6423919247759472,
              0.2892782641320659
            ]
          },
          {
            "start_time": 1770128954.25104,
            "end_time": 1770128963.449496,
            "forecaster_count": 68,
            "interval_lower_bounds": [
              0.15357491469787934,
              0.46876013733728294,
              0.14454095142209913
            ],
            "centers": [
              0.21204379562043799,
              0.5872048829599799,
              0.20075132141958216
            ],
            "interval_upper_bounds": [
              0.24993564548870553,
              0.6444197177099266,
              0.30112698212937317
            ]
          },
          {
            "start_time": 1770128963.449496,
            "end_time": 1770128964.816459,
            "forecaster_count": 69,
            "interval_lower_bounds": [
              0.15599999999999997,
              0.474,
              0.14999999999999994
            ],
            "centers": [
              0.21000000000000005,
              0.59,
              0.19999999999999998
            ],
            "interval_upper_bounds": [
              0.24799999999999997,
              0.6439999999999999,
              0.28999999999999987
            ]
          },
          {
            "start_time": 1770128964.816459,
            "end_time": 1770128985.73705,
            "forecaster_count": 70,
            "interval_lower_bounds": [
              0.15658618753509262,
              0.47177144442938546,
              0.15056349106468658
            ],
            "centers": [
              0.21204379562043799,
              0.5872048829599799,
              0.20075132141958216
            ],
            "interval_upper_bounds": [
              0.25093940310110996,
              0.6464272557713282,
              0.29108941605839406
            ]
          },
          {
            "start_time": 1770128985.73705,
            "end_time": 1770129025.95398,
            "forecaster_count": 71,
            "interval_lower_bounds": [
              0.157176851053711,
              0.4634805980031712,
              0.15113125315816064
            ],
            "centers": [
              0.21410308236483072,
              0.5843885800909551,
              0.20150833754421427
            ],
            "interval_upper_bounds": [
              0.251885979252742,
              0.6488728372044398,
              0.2921870894391106
            ]
          },
          {
            "start_time": 1770129025.95398,
            "end_time": 1770129051.36537,
            "forecaster_count": 72,
            "interval_lower_bounds": [
              0.1648916986578785,
              0.4658599945132063,
              0.14478268762080843
            ],
            "centers": [
              0.21575006303050673,
              0.5831628708294814,
              0.20108706614001173
            ],
            "interval_upper_bounds": [
              0.2513592967345709,
              0.6455009708147017,
              0.2815218925960164
            ]
          },
          {
            "start_time": 1770129051.36537,
            "end_time": 1770129080.164067,
            "forecaster_count": 73,
            "interval_lower_bounds": [
              0.157176851053711,
              0.46348059800317115,
              0.15113125315816064
            ],
            "centers": [
              0.21410308236483072,
              0.584388580090955,
              0.20150833754421427
            ],
            "interval_upper_bounds": [
              0.251885979252742,
              0.6448425711348469,
              0.2921870894391106
            ]
          },
          {
            "start_time": 1770129080.164067,
            "end_time": 1770129105.584014,
            "forecaster_count": 74,
            "interval_lower_bounds": [
              0.15716373034644865,
              0.45336679657621565,
              0.15111858947368417
            ],
            "centers": [
              0.21618408421052634,
              0.5823244631578948,
              0.20149145263157897
            ],
            "interval_upper_bounds": [
              0.2518649524782831,
              0.6447883329083957,
              0.31231175157894736
            ]
          },
          {
            "start_time": 1770129105.584014,
            "end_time": 1770129111.675368,
            "forecaster_count": 74,
            "interval_lower_bounds": [
              0.15752031872014846,
              0.4342026459646505,
              0.15146125928426735
            ],
            "centers": [
              0.21945138419986493,
              0.5786002700877785,
              0.2019483457123565
            ],
            "interval_upper_bounds": [
              0.2524364082053661,
              0.6462551009706426,
              0.3365805761872608
            ]
          },
          {
            "start_time": 1770129111.675368,
            "end_time": 1770129335.557379,
            "forecaster_count": 75,
            "interval_lower_bounds": [
              0.15202382503975187,
              0.41352062637107845,
              0.15202304303625885
            ],
            "centers": [
              0.21958996950186374,
              0.5777126397831244,
              0.20269739071501186
            ],
            "interval_upper_bounds": [
              0.25337304173291975,
              0.64865980607228,
              0.3506664859369705
            ]
          },
          {
            "start_time": 1770129335.557379,
            "end_time": 1770129358.098164,
            "forecaster_count": 76,
            "interval_lower_bounds": [
              0.15574734126967557,
              0.4265451652740712,
              0.14658469707283864
            ],
            "centers": [
              0.22123587474472428,
              0.5751742682096664,
              0.20358985704560925
            ],
            "interval_upper_bounds": [
              0.2544891197216921,
              0.6464347970144039,
              0.3457634405491264
            ]
          },
          {
            "start_time": 1770129358.098164,
            "end_time": 1770129452.835023,
            "forecaster_count": 77,
            "interval_lower_bounds": [
              0.15950385321100916,
              0.439685238095238,
              0.15336769230769226
            ],
            "centers": [
              0.2228964102564102,
              0.5726133333333333,
              0.2044902564102564
            ],
            "interval_upper_bounds": [
              0.2556151493766172,
              0.6441899999999999,
              0.3408170940170939
            ]
          },
          {
            "start_time": 1770129452.835023,
            "end_time": 1770129475.488064,
            "forecaster_count": 78,
            "interval_lower_bounds": [
              0.15961244960111154,
              0.4174746688822638,
              0.1534721176873075
            ],
            "centers": [
              0.22236606226479638,
              0.5730044474854601,
              0.2046294902497434
            ],
            "interval_upper_bounds": [
              0.25578918205306334,
              0.6446300034211426,
              0.35400901813205604
            ]
          },
          {
            "start_time": 1770129475.488064,
            "end_time": 1770129513.513816,
            "forecaster_count": 79,
            "interval_lower_bounds": [
              0.15357806862770917,
              0.41571217048955833,
              0.15357668606641556
            ],
            "centers": [
              0.2218349880178021,
              0.573396097226977,
              0.20476891475522083
            ],
            "interval_upper_bounds": [
              0.2559634477128486,
              0.6450706093803492,
              0.3562979116740842
            ]
          },
          {
            "start_time": 1770129513.513816,
            "end_time": 1770129575.53827,
            "forecaster_count": 80,
            "interval_lower_bounds": [
              0.14877552988357676,
              0.41352367346501173,
              0.15390438716871083
            ],
            "centers": [
              0.22017068359207476,
              0.574623466849644,
              0.20520584955828114
            ],
            "interval_upper_bounds": [
              0.25650953428202883,
              0.6464514002058496,
              0.35808420747920056
            ]
          },
          {
            "start_time": 1770129575.53827,
            "end_time": 1770129596.945165,
            "forecaster_count": 81,
            "interval_lower_bounds": [
              0.1542347480508449,
              0.41132579385544826,
              0.15423349664775657
            ],
            "centers": [
              0.2184992264053636,
              0.5758561113976277,
              0.20564466219700878
            ],
            "interval_upper_bounds": [
              0.25705791341807477,
              0.6478381253223311,
              0.3598781588447653
            ]
          },
          {
            "start_time": 1770129596.945165,
            "end_time": 1770129605.670746,
            "forecaster_count": 82,
            "interval_lower_bounds": [
              0.1544328280906962,
              0.4118558887536424,
              0.15443164213787755
            ],
            "centers": [
              0.2174928995610638,
              0.5765982442550994,
              0.2059088561838368
            ],
            "interval_upper_bounds": [
              0.2573880468178269,
              0.6486730247869869,
              0.3603404983217144
            ]
          },
          {
            "start_time": 1770129605.670746,
            "end_time": 1770129671.968092,
            "forecaster_count": 83,
            "interval_lower_bounds": [
              0.1542347480508449,
              0.41132579385544826,
              0.15423349664775654
            ],
            "centers": [
              0.2184992264053636,
              0.5758561113976277,
              0.20564466219700878
            ],
            "interval_upper_bounds": [
              0.25705791341807477,
              0.6478381253223312,
              0.3598781588447653
            ]
          },
          {
            "start_time": 1770129671.968092,
            "end_time": 1770129690.611365,
            "forecaster_count": 84,
            "interval_lower_bounds": [
              0.1570213531606344,
              0.41362283539477457,
              0.15394117722756984
            ],
            "centers": [
              0.2199838369279868,
              0.57476126010192,
              0.20525490297009316
            ],
            "interval_upper_bounds": [
              0.2565708384977686,
              0.64660641761466,
              0.35816980568281254
            ]
          },
          {
            "start_time": 1770129690.611365,
            "end_time": 1770129921.481423,
            "forecaster_count": 85,
            "interval_lower_bounds": [
              0.15979739725855518,
              0.40976469379367036,
              0.15364996917385942
            ],
            "centers": [
              0.22146280312371552,
              0.5736705713111385,
              0.20486662556514593
            ],
            "interval_upper_bounds": [
              0.25608557252973585,
              0.6453793927250308,
              0.3564679284833539
            ]
          },
          {
            "start_time": 1770129921.481423,
            "end_time": 1770130051.540174,
            "forecaster_count": 86,
            "interval_lower_bounds": [
              0.16075920946257083,
              0.4122382478572886,
              0.15457462397270894
            ],
            "centers": [
              0.2208893368480901,
              0.5730111645216313,
              0.2060994986302786
            ],
            "interval_upper_bounds": [
              0.2576269382412994,
              0.6492752403752295,
              0.36067412260298753
            ]
          },
          {
            "start_time": 1770130051.540174,
            "end_time": 1770130763.272081,
            "forecaster_count": 87,
            "interval_lower_bounds": [
              0.16111588746279887,
              0.4131547415268743,
              0.15491727103191053
            ],
            "centers": [
              0.22329009531703276,
              0.5701535433070866,
              0.2065563613758807
            ],
            "interval_upper_bounds": [
              0.2581985376006392,
              0.6507187179048272,
              0.3614736324077912
            ]
          },
          {
            "start_time": 1770130763.272081,
            "end_time": 1770130836.876607,
            "forecaster_count": 88,
            "interval_lower_bounds": [
              0.15766768620367524,
              0.41223824785728863,
              0.1545746239727089
            ],
            "centers": [
              0.2208893368480901,
              0.5730111645216313,
              0.2060994986302786
            ],
            "interval_upper_bounds": [
              0.2576269382412994,
              0.6492752403752297,
              0.35964362510983616
            ]
          },
          {
            "start_time": 1770130836.876607,
            "end_time": 1770130876.454709,
            "forecaster_count": 89,
            "interval_lower_bounds": [
              0.16111588746279887,
              0.4131547415268743,
              0.15491727103191053
            ],
            "centers": [
              0.22329009531703276,
              0.5701535433070866,
              0.2065563613758807
            ],
            "interval_upper_bounds": [
              0.2581985376006392,
              0.6507187179048272,
              0.3614736324077912
            ]
          },
          {
            "start_time": 1770130876.454709,
            "end_time": 1770131016.676056,
            "forecaster_count": 90,
            "interval_lower_bounds": [
              0.15699979458569638,
              0.4061573764363608,
              0.1569974405418176
            ],
            "centers": [
              0.22435270646296004,
              0.5663173728146164,
              0.20932992072242348
            ],
            "interval_upper_bounds": [
              0.2616663243094939,
              0.6594823380281115,
              0.37679385730036224
            ]
          },
          {
            "start_time": 1770131016.676056,
            "end_time": 1770131351.843196,
            "forecaster_count": 91,
            "interval_lower_bounds": [
              0.15807629840653664,
              0.41170186871780456,
              0.15913451303885046
            ],
            "centers": [
              0.22544438531133584,
              0.5623762639701969,
              0.2121793507184673
            ],
            "interval_upper_bounds": [
              0.26522868860157156,
              0.6684849930211774,
              0.4179933209153806
            ]
          },
          {
            "start_time": 1770131351.843196,
            "end_time": 1770131376.580407,
            "forecaster_count": 92,
            "interval_lower_bounds": [
              0.15432402195673642,
              0.41445366805709694,
              0.16019521832306455
            ],
            "centers": [
              0.2256121082239486,
              0.5607942673452987,
              0.21359362443075272
            ],
            "interval_upper_bounds": [
              0.2669965777798208,
              0.6702826719222379,
              0.42398334449504416
            ]
          },
          {
            "start_time": 1770131376.580407,
            "end_time": 1770131406.171041,
            "forecaster_count": 93,
            "interval_lower_bounds": [
              0.15976941429611113,
              0.4161222534861588,
              0.16083848843464232
            ],
            "centers": [
              0.2278590640129102,
              0.5576896180742335,
              0.2144513179128564
            ],
            "interval_upper_bounds": [
              0.26806948707401196,
              0.6703000217238383,
              0.42246909628832713
            ]
          },
          {
            "start_time": 1770131406.171041,
            "end_time": 1770132638.171255,
            "forecaster_count": 94,
            "interval_lower_bounds": [
              0.16031077825138448,
              0.41753416357444206,
              0.16138286015005127
            ],
            "centers": [
              0.2306215793166729,
              0.554201273816592,
              0.215177146866735
            ],
            "interval_upper_bounds": [
              0.26897781585802766,
              0.6725743614279027,
              0.42389897932746795
            ]
          },
          {
            "start_time": 1770132638.171255,
            "end_time": null,
            "forecaster_count": 95,
            "interval_lower_bounds": [
              0.16085586954116873,
              0.41031738709348553,
              0.16193094670710567
            ],
            "centers": [
              0.23340294627383007,
              0.5506891247833623,
              0.21590792894280758
            ],
            "interval_upper_bounds": [
              0.269892398559008,
              0.6748641235090221,
              0.42533862001733097
            ]
          }
        ],
        "latest": {
          "start_time": 1770132638.171255,
          "end_time": null,
          "forecaster_count": 95,
          "interval_lower_bounds": [
            0.16085586954116873,
            0.41031738709348553,
            0.16193094670710567
          ],
          "centers": [
            0.23340294627383007,
            0.5506891247833623,
            0.21590792894280758
          ],
          "interval_upper_bounds": [
            0.269892398559008,
            0.6748641235090221,
            0.42533862001733097
          ],
          "forecast_values": [
            0.23340294627383007,
            0.5506891247833623,
            0.21590792894280758
          ],
          "means": [
            0.2069452130525199,
            0.4707004479071287,
            0.32235433904035143
          ],
          "histogram": null
        },
        "score_data": {},
        "movement": {
          "divergence": 0.0,
          "direction": "unchanged",
          "movement": 0.0,
          "period": "3600.0",
          "option_index": 0
        }
      }
    },
    "average_coverage": null,
    "my_forecasts": {
      "history": [
        {
          "question_id": 41729,
          "author_id": 290288,
          "start_time": 1770129671.968092,
          "end_time": null,
          "forecast_values": [
            0.24400000000000002,
            0.424,
            0.332
          ],
          "interval_lower_bounds": null,
          "centers": null,
          "interval_upper_bounds": null,
          "distribution_input": null
        }
      ],
      "latest": {
        "question_id": 41729,
        "author_id": 290288,
        "start_time": 1770129671.968092,
        "end_time": null,
        "forecast_values": [
          0.24400000000000002,
          0.424,
          0.332
        ],
        "interval_lower_bounds": null,
        "centers": null,
        "interval_upper_bounds": null,
        "distribution_input": null
      },
      "score_data": {}
    }
  },
  "user_permission": "forecaster",
  "vote": {
    "score": 0,
    "user_vote": null
  },
  "forecasts_count": 96,
  "subscriptions": [],
  "unread_comment_count": 0,
  "last_viewed_at": "2026-02-03T23:56:28.557047Z",
  "private_note": null,
  "key_factors": [],
  "is_current_content_translated": false
}